setup.py
cherrybase/__init__.py
cherrybase/base.py
cherrybase/compat.py
cherrybase/conf.py
cherrybase/plugins.py
cherrybase/rpc.py
cherrybase/utils.py
cherrybase.egg-info/PKG-INFO
cherrybase.egg-info/SOURCES.txt
cherrybase.egg-info/dependency_links.txt
cherrybase.egg-info/requires.txt
cherrybase.egg-info/top_level.txt
cherrybase/db/__init__.py
cherrybase/db/base.py
cherrybase/db/drivers/__init__.py
cherrybase/db/drivers/mongodb.py
cherrybase/db/drivers/mysql.py
cherrybase/db/drivers/pgsql.py
cherrybase/db/drivers/sqlite.py
cherrybase/orm/__init__.py
cherrybase/orm/base.py
cherrybase/orm/drivers/__init__.py
cherrybase/orm/drivers/alchemy.py
cherrybase/tools/__init__.py
cherrybase/tools/jinja.py
cherrybase/tools/auth/__init__.py
cherrybase/tools/auth/base.py
cherrybase/tools/auth/controller.py
scripts/cherrybased